[{"userID":"100003576","name":"J Barria","time":"05 @ 16:18:14"},{"type":1,"set":[{"name":"text visualization (1)","type":2}],"check":false,"usedSets":[{"name":"top-10 agent (10)","type":0},{"name":"user modeling (1)","type":2},{"name":"visual text analytics (2)","type":2},{"name":"visualization (3)","type":2},{"name":"P Brusilovsky (0/18)","type":1}],"time":"05 @ 16:18:23"},{"type":1,"set":[{"name":"user modeling (1)","type":2}],"check":false,"usedSets":[{"name":"top-10 agent (10)","type":0},{"name":"visual text analytics (2)","type":2},{"name":"visualization (3)","type":2},{"name":"P Brusilovsky (0/18)","type":1}],"time":"05 @ 16:18:24"},{"type":1,"set":[{"name":"visual text analytics (2)","type":2}],"check":false,"usedSets":[{"name":"top-10 agent (10)","type":0},{"name":"visualization (3)","type":2},{"name":"P Brusilovsky (0/18)","type":1}],"time":"05 @ 16:18:24"},{"type":1,"set":[{"name":"visualization (3)","type":2}],"check":false,"usedSets":[{"name":"top-10 agent (10)","type":0},{"name":"P Brusilovsky (0/18)","type":1}],"time":"05 @ 16:18:26"},{"type":4,"setsCombination":[[{"name":"P Brusilovsky (0/18)","type":1,"state":1},{"name":"top-10 agent (10)","type":0,"state":1}]],"group_type":"NONQUERY_GROUP","query_header":"normal","Items":["10815","10816","10758","10777","10804","10762","10794","10781","10784","10817"],"time":"05 @ 16:18:28"}]