[{"userID":"100004423","name":"C He","time":"11 @ 14:23:08"},{"type":3,"setsCombination":[[{"name":"P Brusilovsky (4/28)","type":1,"state":1},{"name":"D Parra (3/8)","type":1,"state":1},{"name":"ext. bookmarks agent (10)","type":0,"state":1},{"name":"bookmark-based agent (10)","type":0,"state":1},{"name":"top-10 agent (10)","type":0,"state":1}]],"itemNumber":1,"group_type":"NONQUERY_GROUP","time":"11 @ 14:23:05"},{"type":4,"setsCombination":[[{"name":"P Brusilovsky (4/28)","type":1,"state":1},{"name":"ext. bookmarks agent (10)","type":0,"state":1},{"name":"bookmark-based agent (10)","type":0,"state":1},{"name":"tag-based agent (10)","type":0,"state":1}]],"group_type":"NONQUERY_GROUP","query_header":"normal","Items":["10763"],"time":"11 @ 14:23:25"},{"type":3,"setsCombination":[[{"name":"P Brusilovsky (4/28)","type":1,"state":1},{"name":"ext. bookmarks agent (10)","type":0,"state":1},{"name":"bookmark-based agent (10)","type":0,"state":1},{"name":"tag-based agent (10)","type":0,"state":1}]],"itemNumber":1,"group_type":"NONQUERY_GROUP","time":"11 @ 14:23:21"},{"type":1,"set":[{"name":"emotion visualization (1)","type":2}],"check":true,"usedSets":[{"name":"top-10 agent (10)","type":0},{"name":"tag-based agent (10)","type":0},{"name":"bookmark-based agent (10)","type":0},{"name":"ext. bookmarks agent (10)","type":0},{"name":"C He (4/4)","type":1},{"name":"D Parra (3/8)","type":1},{"name":"P Brusilovsky (4/28)","type":1},{"name":"emotion visualization (1)","type":2}],"time":"11 @ 14:23:36"},{"type":1,"set":[{"name":"excitement visualization (1)","type":2}],"check":true,"usedSets":[{"name":"top-10 agent (10)","type":0},{"name":"tag-based agent (10)","type":0},{"name":"bookmark-based agent (10)","type":0},{"name":"ext. bookmarks agent (10)","type":0},{"name":"C He (4/4)","type":1},{"name":"D Parra (3/8)","type":1},{"name":"P Brusilovsky (4/28)","type":1},{"name":"emotion visualization (1)","type":2},{"name":"excitement visualization (1)","type":2}],"time":"11 @ 14:23:39"}]